rpn_calc/__init__.py
rpn_calc/__main__.py
rpn_calc/calculator.py
rpn_calc-0.2.3.dist-info/LICENSE
rpn_calc-0.2.3.dist-info/METADATA
rpn_calc-0.2.3.dist-info/WHEEL
rpn_calc-0.2.3.dist-info/entry_points.txt
rpn_calc-0.2.3.dist-info/top_level.txt
rpn_calc-0.2.3.dist-info/RECORD
