Metadata-Version: 2.1
Name: rpn-calc
Version: 0.2.3
Summary: RPN calculator
Home-page: https://github.com/Allain18/pol
Author: Alain Girard
Author-email: alaingirardvd@gmail.com
License: MIT License
Keywords: rpn,calculator,reverse polish notation
Classifier: Development Status :: 4 - Beta
Classifier: Intended Audience :: Developers
Classifier: License :: OSI Approved :: MIT License
Classifier: Natural Language :: English
Classifier: Programming Language :: Python :: 3.6
Classifier: Programming Language :: Python :: 3.7
Classifier: Programming Language :: Python :: 3.8
Classifier: Programming Language :: Python :: 3.9
Classifier: Programming Language :: Python :: 3.10
Classifier: Programming Language :: Python :: 3.11
Classifier: Programming Language :: Python :: Implementation :: PyPy
Classifier: Environment :: Console
Classifier: Operating System :: OS Independent
Requires-Python: >=3.6
License-File: LICENSE
Requires-Dist: pyyaml (>=5.0)
